scim2_client/__init__.py
scim2_client/client.py
scim2_client/engines/__init__.py
scim2_client/engines/httpx.py
scim2_client/engines/werkzeug.py
scim2_client/errors.py
scim2_client/py.typed
scim2_client-0.7.1.dist-info/WHEEL
scim2_client-0.7.1.dist-info/METADATA
scim2_client-0.7.1.dist-info/RECORD
