Metadata-Version: 2.3
Name: scim2-client
Version: 0.7.1
Summary: Pythonically build SCIM requests and parse SCIM responses
Keywords: scim,scim2,provisioning,rfc7643,rfc7644,httpx,api
Author: Yaal Coop
Author-email: Yaal Coop <contact@yaal.coop>
License:                                  Apache License
Classifier: Intended Audience :: Developers
Classifier: Development Status :: 3 - Alpha
Classifier: Programming Language :: Python :: 3.10
Classifier: Programming Language :: Python :: 3.11
Classifier: Programming Language :: Python :: 3.12
Classifier: Programming Language :: Python :: 3.13
Classifier: Programming Language :: Python :: 3.14
Classifier: Programming Language :: Python :: Implementation :: CPython
Classifier: License :: OSI Approved :: Apache Software License
Classifier: Environment :: Web Environment
Classifier: Programming Language :: Python
Classifier: Operating System :: OS Independent
Requires-Dist: scim2-models>=0.6.1
Requires-Dist: httpx>=0.28.0 ; extra == 'httpx'
Requires-Dist: werkzeug>=3.1.3 ; extra == 'werkzeug'
Requires-Python: >=3.10
Project-URL: changelog, https://scim2-client.readthedocs.io/en/latest/changelog.html
Project-URL: documentation, https://scim2-client.readthedocs.io
Project-URL: funding, https://github.com/sponsors/python-scim
Project-URL: repository, https://github.com/python-scim/scim2-client
Provides-Extra: httpx
Provides-Extra: werkzeug
